windows_cap-0.1.2.dist-info/METADATA
windows_cap-0.1.2.dist-info/WHEEL
windows_cap-0.1.2.dist-info/license_files/LICENSE
windows_cap/__init__.py
windows_cap/windows_cap.cp38-win_amd64.pyd
windows_cap-0.1.2.dist-info/RECORD
